pr_assistant_pkg/__init__.py
pr_assistant_pkg/local_storage.txt
pr_assistant_pkg/local_storage_emails.txt
pr_assistant_pkg/main.py
pr_assistant_pkg/prompt.txt
pr_assistant_pkg/setup.sh
pr_assistant_pkg-0.1.3.dist-info/METADATA
pr_assistant_pkg-0.1.3.dist-info/WHEEL
pr_assistant_pkg-0.1.3.dist-info/entry_points.txt
pr_assistant_pkg-0.1.3.dist-info/RECORD
