Metadata-Version: 2.1
Name: pr-assistant-pkg
Version: 0.1.3
Summary: 
Author: Ahmed Abdul Saad
Requires-Python: >=3.12,<4.0
Classifier: Programming Language :: Python :: 3
Classifier: Programming Language :: Python :: 3.12
Requires-Dist: argparse (>=1.4.0,<2.0.0)
Requires-Dist: chevron (>=0.14.0,<0.15.0)
Requires-Dist: openai (>=1.35.3,<2.0.0)
